ffbb_api_client_v2/__init__.py
ffbb_api_client_v2/clients/__init__.py
ffbb_api_client_v2/clients/api_ffbb_app_client.py
ffbb_api_client_v2/clients/ffbb_api_client_v2.py
ffbb_api_client_v2/clients/meilisearch_client.py
ffbb_api_client_v2/clients/meilisearch_ffbb_client.py
ffbb_api_client_v2/helpers/__init__.py
ffbb_api_client_v2/helpers/http_requests_helper.py
ffbb_api_client_v2/helpers/http_requests_utils.py
ffbb_api_client_v2/helpers/meilisearch_client_extension.py
ffbb_api_client_v2/helpers/multi_search_query_helper.py
ffbb_api_client_v2/models/__init__.py
ffbb_api_client_v2/models/affiche.py
ffbb_api_client_v2/models/cartographie.py
ffbb_api_client_v2/models/categorie.py
ffbb_api_client_v2/models/code.py
ffbb_api_client_v2/models/commune.py
ffbb_api_client_v2/models/competition_id.py
ffbb_api_client_v2/models/competition_id_categorie.py
ffbb_api_client_v2/models/competition_id_sexe.py
ffbb_api_client_v2/models/competition_id_type_competition.py
ffbb_api_client_v2/models/competition_id_type_competition_generique.py
ffbb_api_client_v2/models/competition_origine.py
ffbb_api_client_v2/models/competition_origine_categorie.py
ffbb_api_client_v2/models/competition_origine_type_competition.py
ffbb_api_client_v2/models/competition_origine_type_competition_generique.py
ffbb_api_client_v2/models/competition_type.py
ffbb_api_client_v2/models/competitions_models.py
ffbb_api_client_v2/models/coordonnees.py
ffbb_api_client_v2/models/coordonnees_type.py
ffbb_api_client_v2/models/document_flyer.py
ffbb_api_client_v2/models/document_flyer_type.py
ffbb_api_client_v2/models/etat.py
ffbb_api_client_v2/models/external_id.py
ffbb_api_client_v2/models/facet_distribution.py
ffbb_api_client_v2/models/facet_stats.py
ffbb_api_client_v2/models/folder.py
ffbb_api_client_v2/models/game_stats_models.py
ffbb_api_client_v2/models/geo.py
ffbb_api_client_v2/models/gradient_color.py
ffbb_api_client_v2/models/hit.py
ffbb_api_client_v2/models/id_engagement_equipe.py
ffbb_api_client_v2-1.1.1.dist-info/licenses/LICENSE.txt
ffbb_api_client_v2-1.1.1.dist-info/METADATA
ffbb_api_client_v2-1.1.1.dist-info/WHEEL
ffbb_api_client_v2-1.1.1.dist-info/top_level.txt
ffbb_api_client_v2-1.1.1.dist-info/RECORD
