Metadata-Version: 2.4
Name: ffbb_api_client_v2
Version: 1.1.1
Summary: Modern Python client library for FFBB (French Basketball Federation) APIs with type-safe models, flexible field selection, and comprehensive testing
Home-page: https://github.com/Rinzler78/FFBBApiClientV2_Python
Author: Rinzler78
Author-email: Borisleclere@gmail.com
License: Apache-2.0
Project-URL: Documentation, https://github.com/Rinzler78/FFBBApiClientV2_Python/blob/main/README.rst
Project-URL: Source, https://github.com/Rinzler78/FFBBApiClientV2_Python
Project-URL: Changelog, https://github.com/Rinzler78/FFBBApiClientV2_Python/blob/main/CHANGELOG.md
Project-URL: Tracker, https://github.com/Rinzler78/FFBBApiClientV2_Python/issues
Project-URL: Release Notes, https://github.com/Rinzler78/FFBBApiClientV2_Python/blob/main/RELEASE_NOTES.md
Platform: any
Classifier: Development Status :: 4 - Beta
Classifier: Programming Language :: Python
Classifier: Programming Language :: Python :: 3
Classifier: Programming Language :: Python :: 3.9
Classifier: Programming Language :: Python :: 3.10
Classifier: Programming Language :: Python :: 3.11
Classifier: Programming Language :: Python :: 3.12
Classifier: Intended Audience :: Developers
Classifier: Topic :: Software Development :: Libraries :: Python Modules
Classifier: Topic :: Internet :: WWW/HTTP :: Dynamic Content
Classifier: License :: OSI Approved :: Apache Software License
Requires-Python: >=3.9
License-File: LICENSE.txt
Requires-Dist: importlib-metadata; python_version < "3.8"
Requires-Dist: requests
Requires-Dist: python-dotenv
Requires-Dist: readme_renderer
Requires-Dist: python-dateutil
Requires-Dist: requests_cache
Provides-Extra: testing
Requires-Dist: setuptools; extra == "testing"
Requires-Dist: coverage; extra == "testing"
Dynamic: license-file
